pymysqlreplication/__init__.py
pymysqlreplication/binlogstream.py
pymysqlreplication/bitmap.py
pymysqlreplication/column.py
pymysqlreplication/event.py
pymysqlreplication/exceptions.py
pymysqlreplication/gtid.py
pymysqlreplication/json_binary.py
pymysqlreplication/logger.py
pymysqlreplication/packet.py
pymysqlreplication/row_event.py
pymysqlreplication/table.py
pymysqlreplication/constants/BINLOG.py
pymysqlreplication/constants/CHARSET.py
pymysqlreplication/constants/FIELD_TYPE.py
pymysqlreplication/constants/NONE_SOURCE.py
pymysqlreplication/constants/STATUS_VAR_KEY.py
pymysqlreplication/constants/__init__.py
pymysqlreplication/tests/__init__.py
pymysqlreplication/tests/base.py
pymysqlreplication/tests/benchmark.py
pymysqlreplication/tests/binlogfilereader.py
pymysqlreplication/tests/conftest.py
pymysqlreplication/tests/test_abnormal.py
pymysqlreplication/tests/test_basic.py
pymysqlreplication/tests/test_data_objects.py
pymysqlreplication/tests/test_data_type.py
pymysqlreplication/tests/test_event.py
pymysqlreplication/tests/test_util_bytes.py
pymysqlreplication/util/__init__.py
pymysqlreplication/util/bytes.py
mysql_replication-1.0.14.dist-info/METADATA
mysql_replication-1.0.14.dist-info/WHEEL
mysql_replication-1.0.14.dist-info/top_level.txt
mysql_replication-1.0.14.dist-info/RECORD
