Metadata-Version: 2.4
Name: mysql-replication
Version: 1.0.14
Summary: Pure Python Implementation of MySQL replication protocol build on top of PyMYSQL.
Home-page: https://github.com/julien-duponchelle/python-mysql-replication
Author: Julien Duponchelle
Author-email: julien@duponchelle.info
License: Apache 2
Requires-Dist: packaging
Requires-Dist: pymysql>=1.1.0
Dynamic: author
Dynamic: author-email
Dynamic: description
Dynamic: description-content-type
Dynamic: home-page
Dynamic: license
Dynamic: requires-dist
Dynamic: summary
